CHANGES.rst
LICENSE.GPL
LICENSE.rst
MANIFEST.in
README.rst
setup.py
collective/__init__.py
collective.portlet.carousel.egg-info/PKG-INFO
collective.portlet.carousel.egg-info/SOURCES.txt
collective.portlet.carousel.egg-info/dependency_links.txt
collective.portlet.carousel.egg-info/entry_points.txt
collective.portlet.carousel.egg-info/namespace_packages.txt
collective.portlet.carousel.egg-info/not-zip-safe
collective.portlet.carousel.egg-info/requires.txt
collective.portlet.carousel.egg-info/top_level.txt
collective/portlet/__init__.py
collective/portlet/carousel/__init__.py
collective/portlet/carousel/browser.py
collective/portlet/carousel/configure.zcml
collective/portlet/carousel/i18n.py
collective/portlet/carousel/interfaces.py
collective/portlet/carousel/portlet.pt
collective/portlet/carousel/portlet.py
collective/portlet/carousel/renderer_behavior.pt
collective/portlet/carousel/renderer_dublincore.pt
collective/portlet/carousel/widgets.py
collective/portlet/carousel/locales/collective.portlet.carousel.pot
collective/portlet/carousel/locales/plone.pot
collective/portlet/carousel/locales/da/LC_MESSAGES/collective.portlet.carousel.po
collective/portlet/carousel/locales/da/LC_MESSAGES/plone.po
collective/portlet/carousel/locales/fi/LC_MESSAGES/collective.portlet.carousel.po
collective/portlet/carousel/profile/portlets.xml