Metadata-Version: 1.1
Name: collective.portlet.carousel
Version: 1.1.3
Summary: Carousel for collective.panels
Home-page: https://pypi.python.org/pypi/collective.portlet.carousel
Author: Bo Simonsen
Author-email: bo@headnet.dk
License: GPL version 2
Keywords: Python Plone portlets carousel panels
Platform: UNKNOWN
Classifier: Environment :: Web Environment
Classifier: Framework :: Plone
Classifier: Framework :: Plone :: 5.1
Classifier: Framework :: Plone :: 4.3
Classifier: Programming Language :: Python
Classifier: Programming Language :: Python :: 2.7
Classifier: Operating System :: OS Independent
Classifier: License :: OSI Approved :: GNU General Public License v2 (GPLv2)
